[{"model": "projects.functionalgroup", "pk": 1, "fields": {"name": "Administration and Coordination", "nom": null, "theme": 7, "sections": [1, 2, 3, 8, 5, 7, 14, 9, 11, 13, 4, 6, 16, 12, 25, 23, 49, 24, 22, 41, 40, 37, 39, 38, 33, 35, 36, 34]}}, {"model": "projects.functionalgroup", "pk": 42, "fields": {"name": "Animal Health", "nom": null, "theme": 7, "sections": [23, 49, 30]}}, {"model": "projects.functionalgroup", "pk": 17, "fields": {"name": "Aquaculture", "nom": null, "theme": 3, "sections": [1, 25, 23, 24, 22, 39, 33, 36, 32]}}, {"model": "projects.functionalgroup", "pk": 23, "fields": {"name": "Aquatic Invasive Species (AIS)", "nom": null, "theme": 4, "sections": [22]}}, {"model": "projects.functionalgroup", "pk": 38, "fields": {"name": "Arctic", "nom": null, "theme": 1, "sections": [37, 39, 38]}}, {"model": "projects.functionalgroup", "pk": 62, "fields": {"name": "ARGO", "nom": null, "theme": 6, "sections": [38]}}, {"model": "projects.functionalgroup", "pk": 67, "fields": {"name": "ASEC", "nom": null, "theme": 7, "sections": [4]}}, {"model": "projects.functionalgroup", "pk": 33, "fields": {"name": "AZMP", "nom": null, "theme": 6, "sections": [11]}}, {"model": "projects.functionalgroup", "pk": 16, "fields": {"name": "Bass", "nom": null, "theme": 1, "sections": [13]}}, {"model": "projects.functionalgroup", "pk": 32, "fields": {"name": "Benthic Biodiversity", "nom": null, "theme": 1, "sections": [41]}}, {"model": "projects.functionalgroup", "pk": 61, "fields": {"name": "Biodiversity Facilities", "nom": null, "theme": 6, "sections": [36]}}, {"model": "projects.functionalgroup", "pk": 64, "fields": {"name": "Biotechnology and Genomics", "nom": null, "theme": 6, "sections": [2, 25]}}, {"model": "projects.functionalgroup", "pk": 57, "fields": {"name": "Business Services", "nom": null, "theme": 7, "sections": [25, 49, 54, 53, 30, 32, 58]}}, {"model": "projects.functionalgroup", "pk": 43, "fields": {"name": "Cetaceans", "nom": null, "theme": 1, "sections": [22, 41, 37, 39]}}, {"model": "projects.functionalgroup", "pk": 36, "fields": {"name": "Climate Change", "nom": null, "theme": 4, "sections": [11, 41, 37, 39, 38]}}, {"model": "projects.functionalgroup", "pk": 25, "fields": {"name": "COOGER (Oil and Gas)", "nom": null, "theme": 3, "sections": [38]}}, {"model": "projects.functionalgroup", "pk": 3, "fields": {"name": "Crustaceans, Other", "nom": null, "theme": 1, "sections": [5]}}, {"model": "projects.functionalgroup", "pk": 5, "fields": {"name": "Cumulative Effects", "nom": null, "theme": 3, "sections": [14, 22]}}, {"model": "projects.functionalgroup", "pk": 22, "fields": {"name": "Data Management", "nom": null, "theme": 6, "sections": [16, 49, 24, 37, 39, 54, 33, 35, 53, 36, 34, 31]}}, {"model": "projects.functionalgroup", "pk": 15, "fields": {"name": "Diadromous (non-salmon)", "nom": null, "theme": 1, "sections": [13, 36, 34, 32]}}, {"model": "projects.functionalgroup", "pk": 65, "fields": {"name": "Diagnostic Services", "nom": null, "theme": 7, "sections": [2, 8]}}, {"model": "projects.functionalgroup", "pk": 66, "fields": {"name": "Disease ?", "nom": null, "theme": 7, "sections": [2]}}, {"model": "projects.functionalgroup", "pk": 37, "fields": {"name": "EBFM", "nom": null, "theme": 1, "sections": [41, 37, 33, 35]}}, {"model": "projects.functionalgroup", "pk": 7, "fields": {"name": "Ecologically Significant Areas (ESA)", "nom": null, "theme": null, "sections": [14]}}, {"model": "projects.functionalgroup", "pk": 19, "fields": {"name": "Ecosystem Interactions / Shellfish Fishery", "nom": "", "theme": null, "sections": [1]}}, {"model": "projects.functionalgroup", "pk": 20, "fields": {"name": "Ecosystem Stressors & Reporting", "nom": null, "theme": 3, "sections": [1, 22]}}, {"model": "projects.functionalgroup", "pk": 18, "fields": {"name": "Ecosystem/Oceanographic Modeling", "nom": null, "theme": 6, "sections": [1, 11, 24, 22, 41, 37]}}, {"model": "projects.functionalgroup", "pk": 6, "fields": {"name": "Effectiveness Science & Monitoring", "nom": "", "theme": null, "sections": [14]}}, {"model": "projects.functionalgroup", "pk": 55, "fields": {"name": "Elasmobranchs", "nom": null, "theme": 1, "sections": [33]}}, {"model": "projects.functionalgroup", "pk": 8, "fields": {"name": "Freshwater Habitat Research", "nom": null, "theme": 3, "sections": [14, 34]}}, {"model": "projects.functionalgroup", "pk": 10, "fields": {"name": "Groundfish", "nom": null, "theme": 1, "sections": [9, 33, 36, 34, 32]}}, {"model": "projects.functionalgroup", "pk": 58, "fields": {"name": "Halibut", "nom": null, "theme": 1, "sections": []}}, {"model": "projects.functionalgroup", "pk": 11, "fields": {"name": "Herring", "nom": null, "theme": 1, "sections": [9, 33]}}, {"model": "projects.functionalgroup", "pk": 9, "fields": {"name": "Hydrological Studies", "nom": "", "theme": null, "sections": [14]}}, {"model": "projects.functionalgroup", "pk": 71, "fields": {"name": "Invertebrates", "nom": null, "theme": 1, "sections": [24, 33, 35]}}, {"model": "projects.functionalgroup", "pk": 46, "fields": {"name": "Large Pelagics", "nom": null, "theme": 1, "sections": [33]}}, {"model": "projects.functionalgroup", "pk": 2, "fields": {"name": "Lobster", "nom": null, "theme": 1, "sections": [5]}}, {"model": "projects.functionalgroup", "pk": 69, "fields": {"name": "Marine Fish", "nom": null, "theme": 1, "sections": [9]}}, {"model": "projects.functionalgroup", "pk": 28, "fields": {"name": "Marine Plants (Eelgrass, Rockweed, Kelp)", "nom": null, "theme": 1, "sections": [24, 22, 39]}}, {"model": "projects.functionalgroup", "pk": 21, "fields": {"name": "Marine Protected Areas (MPAs) and Other Effective Measures", "nom": null, "theme": 5, "sections": [1, 49, 24, 22, 41, 37, 39, 35]}}, {"model": "projects.functionalgroup", "pk": 26, "fields": {"name": "Marine Spatial Planning (MSP)", "nom": null, "theme": 5, "sections": [24, 22, 41, 39, 31]}}, {"model": "projects.functionalgroup", "pk": 48, "fields": {"name": "Nutrients", "nom": null, "theme": 3, "sections": [22, 39]}}, {"model": "projects.functionalgroup", "pk": 59, "fields": {"name": "Observer Program", "nom": null, "theme": 6, "sections": [34]}}, {"model": "projects.functionalgroup", "pk": 30, "fields": {"name": "Ocean Acidification", "nom": null, "theme": 4, "sections": [11, 23, 38]}}, {"model": "projects.functionalgroup", "pk": 56, "fields": {"name": "OHS", "nom": null, "theme": 7, "sections": [49, 54, 53, 30]}}, {"model": "projects.functionalgroup", "pk": 73, "fields": {"name": "OPP (Shipping)", "nom": null, "theme": 3, "sections": [24, 41, 37, 38]}}, {"model": "projects.functionalgroup", "pk": 31, "fields": {"name": "OPP - Baseline", "nom": null, "theme": 3, "sections": [24]}}, {"model": "projects.functionalgroup", "pk": 39, "fields": {"name": "OPP - Drift Prediction", "nom": null, "theme": 3, "sections": [11, 37, 38]}}, {"model": "projects.functionalgroup", "pk": 41, "fields": {"name": "OPP - Fate and Behaviour", "nom": null, "theme": 3, "sections": [38]}}, {"model": "projects.functionalgroup", "pk": 40, "fields": {"name": "OPP - MEQ", "nom": null, "theme": 3, "sections": [41]}}, {"model": "projects.functionalgroup", "pk": 35, "fields": {"name": "OPP - Whale Detection and Avoidance", "nom": null, "theme": 3, "sections": [41]}}, {"model": "projects.functionalgroup", "pk": 47, "fields": {"name": "Phytoplankton", "nom": null, "theme": 1, "sections": [39]}}, {"model": "projects.functionalgroup", "pk": 24, "fields": {"name": "PIER", "nom": null, "theme": 2, "sections": [24, 38]}}, {"model": "projects.functionalgroup", "pk": 44, "fields": {"name": "Pinnipeds", "nom": null, "theme": 1, "sections": [34]}}, {"model": "projects.functionalgroup", "pk": 12, "fields": {"name": "Port Sampling", "nom": null, "theme": 1, "sections": [9, 34]}}, {"model": "projects.functionalgroup", "pk": 60, "fields": {"name": "Remote Sensing", "nom": null, "theme": 6, "sections": [39]}}, {"model": "projects.functionalgroup", "pk": 70, "fields": {"name": "RV Survey", "nom": null, "theme": 6, "sections": []}}, {"model": "projects.functionalgroup", "pk": 14, "fields": {"name": "Salmon", "nom": null, "theme": 1, "sections": [13, 36, 32]}}, {"model": "projects.functionalgroup", "pk": 51, "fields": {"name": "Scallop", "nom": null, "theme": 1, "sections": [35]}}, {"model": "projects.functionalgroup", "pk": 54, "fields": {"name": "Secondary Species", "nom": null, "theme": 1, "sections": [33]}}, {"model": "projects.functionalgroup", "pk": 29, "fields": {"name": "Sediment Dynamics", "nom": null, "theme": 3, "sections": [22]}}, {"model": "projects.functionalgroup", "pk": 50, "fields": {"name": "Shrimp", "nom": null, "theme": 1, "sections": [35]}}, {"model": "projects.functionalgroup", "pk": 49, "fields": {"name": "Small Pelagics", "nom": null, "theme": 1, "sections": [33]}}, {"model": "projects.functionalgroup", "pk": 4, "fields": {"name": "Snow Crab", "nom": null, "theme": 1, "sections": [5]}}, {"model": "projects.functionalgroup", "pk": 13, "fields": {"name": "Species at Risk (SAR)", "nom": null, "theme": 1, "sections": [9, 23, 24, 22, 41, 37, 39, 33, 35, 36, 32]}}, {"model": "projects.functionalgroup", "pk": 72, "fields": {"name": "Surveys", "nom": null, "theme": 6, "sections": [24, 39, 34]}}, {"model": "projects.functionalgroup", "pk": 52, "fields": {"name": "Turtles", "nom": null, "theme": 1, "sections": [35]}}]