[{"model": "shared_models.allotmentcategory", "pk": 2, "fields": {"name": "Capital", "color": "#FF4662"}}, {"model": "shared_models.allotmentcategory", "pk": 4, "fields": {"name": "CBase", "color": "#FFC9C1"}}, {"model": "shared_models.allotmentcategory", "pk": 5, "fields": {"name": "G&C", "color": "#D368FF"}}, {"model": "shared_models.allotmentcategory", "pk": 3, "fields": {"name": "O&M", "color": "#3ADDFF"}}, {"model": "shared_models.allotmentcategory", "pk": 1, "fields": {"name": "Salary", "color": "#32B71F"}}]