[
{
    "model": "maret.orgcategory",
    "pk": 1,
    "fields": {
        "name": "Aquaculture industry association",
        "nom": null
    }
},
{
    "model": "maret.orgcategory",
    "pk": 2,
    "fields": {
        "name": "Aquaculture license holder",
        "nom": null
    }
},
{
    "model": "maret.orgcategory",
    "pk": 3,
    "fields": {
        "name": "Biotechnology",
        "nom": null
    }
},
{
    "model": "maret.orgcategory",
    "pk": 4,
    "fields": {
        "name": "Buyer",
        "nom": null
    }
},
{
    "model": "maret.orgcategory",
    "pk": 5,
    "fields": {
        "name": "Charter association",
        "nom": null
    }
},
{
    "model": "maret.orgcategory",
    "pk": 6,
    "fields": {
        "name": "ENGO",
        "nom": null
    }
},
{
    "model": "maret.orgcategory",
    "pk": 7,
    "fields": {
        "name": "Fish harvester",
        "nom": null
    }
},
{
    "model": "maret.orgcategory",
    "pk": 8,
    "fields": {
        "name": "Fish harvesters association",
        "nom": null
    }
},
{
    "model": "maret.orgcategory",
    "pk": 9,
    "fields": {
        "name": "Fish harvesters & processors association",
        "nom": null
    }
},
{
    "model": "maret.orgcategory",
    "pk": 10,
    "fields": {
        "name": "Fish processors association",
        "nom": null
    }
},
{
    "model": "maret.orgcategory",
    "pk": 11,
    "fields": {
        "name": "Fishing industry umbrella organization",
        "nom": null
    }
},
{
    "model": "maret.orgcategory",
    "pk": 12,
    "fields": {
        "name": "Harbour authority",
        "nom": null
    }
},
{
    "model": "maret.orgcategory",
    "pk": 13,
    "fields": {
        "name": "Harvesting & processing",
        "nom": null
    }
},
{
    "model": "maret.orgcategory",
    "pk": 14,
    "fields": {
        "name": "Hatchery",
        "nom": null
    }
},
{
    "model": "maret.orgcategory",
    "pk": 15,
    "fields": {
        "name": "Indigenous ENGO",
        "nom": null
    }
},
{
    "model": "maret.orgcategory",
    "pk": 16,
    "fields": {
        "name": "Industry association รป submarine cables",
        "nom": null
    }
},
{
    "model": "maret.orgcategory",
    "pk": 17,
    "fields": {
        "name": "NGO",
        "nom": null
    }
},
{
    "model": "maret.orgcategory",
    "pk": 18,
    "fields": {
        "name": "Other federal department",
        "nom": null
    }
},
{
    "model": "maret.orgcategory",
    "pk": 19,
    "fields": {
        "name": "Port authority",
        "nom": null
    }
},
{
    "model": "maret.orgcategory",
    "pk": 20,
    "fields": {
        "name": "Processing organization",
        "nom": null
    }
},
{
    "model": "maret.orgcategory",
    "pk": 21,
    "fields": {
        "name": "Ship brokers",
        "nom": null
    }
},
{
    "model": "maret.orgcategory",
    "pk": 22,
    "fields": {
        "name": "Trucking",
        "nom": null
    }
},
{
    "model": "maret.orgcategory",
    "pk": 23,
    "fields": {
        "name": "United States First Nation",
        "nom": null
    }
},
{
    "model": "maret.orgcategory",
    "pk": 24,
    "fields": {
        "name": "United States Government",
        "nom": null
    }
},
{
    "model": "maret.orgcategory",
    "pk": 25,
    "fields": {
        "name": "Utility",
        "nom": null
    }
},
{
    "model": "maret.orgcategory",
    "pk": 26,
    "fields": {
        "name": "Whale disentanglement",
        "nom": null
    }
}
]
